colortimelog/__init__.py
colortimelog/colortimelog.py
colortimelog/colortimelog_test.py
colortimelog-0.0.9.dist-info/LICENSE
colortimelog-0.0.9.dist-info/METADATA
colortimelog-0.0.9.dist-info/WHEEL
colortimelog-0.0.9.dist-info/top_level.txt
colortimelog-0.0.9.dist-info/RECORD
