Metadata-Version: 2.1
Name: colortimelog
Version: 0.0.9
Summary: A util for logging the time elapsed for a task.
Home-page: https://github.com/wq2012/colortimelog
Author: Quan Wang
Author-email: quanw@google.com
Classifier: Programming Language :: Python :: 3
Classifier: License :: OSI Approved :: Apache Software License
Classifier: Operating System :: OS Independent
License-File: LICENSE
